setup.py
dshield_parser/__init__.py
dshield_parser/__main__.py
dshield_parser.egg-info/PKG-INFO
dshield_parser.egg-info/SOURCES.txt
dshield_parser.egg-info/dependency_links.txt
dshield_parser.egg-info/top_level.txt
dshield_parser/cowrie_processor/__init__.py
dshield_parser/cowrie_processor/__main__.py
dshield_parser/cowrie_processor/reports.py
dshield_parser/firewall_processor/__init__.py
dshield_parser/firewall_processor/__main__.py
dshield_parser/firewall_processor/reports.py
dshield_parser/test/__init__.py
dshield_parser/test/test_json.py
dshield_parser/utils/__init__.py
dshield_parser/utils/__main__.py
dshield_parser/utils/enrichment.py
dshield_parser/utils/file_io.py
dshield_parser/utils/graphs.py
dshield_parser/utils/json.py
dshield_parser/utils/ml.py
dshield_parser/utils/sql.py
dshield_parser/utils/ssh.py
dshield_parser/web_processor/__init__.py
dshield_parser/web_processor/__main__.py
dshield_parser/web_processor/reports.py